{"attempt":1,"authorization":{"action":"retry-stage","actorId":"pipeline-system","actorType":"system","authorized":true,"decision":"allow","decisionId":"pipeline-authorization-c502ceb4","evaluatedAt":"2026-07-15T12:05:09.730Z","evidence":["source:pipeline-composition"],"executionFingerprint":"pipeline-execution-e037fc56","grantedCapabilities":[],"idempotencyKey":"pipeline-idempotency-c502ceb4","missingCapabilities":[],"operation":"pipeline.stage.resume","policyVersion":"pipeline-durable-v1","projectSlug":"fatih-sultan-mehmet-in-i-stanbul-un-fethine-hazirlanisi-cfe77fd8-8350-4415-bc87-211e3d36c4d5","reason":"trusted pipeline composition","reasonCode":"AUTHORIZED","requestId":"pipeline-request-c502ceb4","requiredCapabilities":[],"requiredConfirmationLevel":"high","requiresConfirmation":true,"risk":"high","schemaVersion":"1","stage":"scenes"},"confirmation":{"action":"retry-stage","actorId":"pipeline-system","authorizationDecisionId":"pipeline-authorization-c502ceb4","bindingFingerprint":"pipeline-confirmation-binding-c502ceb4","bindingMatches":true,"confirmationId":"pipeline-confirmation-c502ceb4","confirmationRequestId":"pipeline-confirmation-request-c502ceb4","consumed":false,"decision":"valid","evaluatedAt":"2026-07-15T12:05:09.730Z","evidence":["source:pipeline-composition"],"expired":false,"idempotencyKey":"pipeline-idempotency-c502ceb4","operation":"pipeline.stage.resume","policyVersion":"pipeline-durable-v1","projectSlug":"fatih-sultan-mehmet-in-i-stanbul-un-fethine-hazirlanisi-cfe77fd8-8350-4415-bc87-211e3d36c4d5","providedConfirmationLevel":"high","reason":"trusted pipeline composition","reasonCode":"CONFIRMATION_VALID","requestId":"pipeline-request-c502ceb4","requiredConfirmationLevel":"high","riskLevel":"high","schemaVersion":"1","singleUse":true,"stage":"scenes","valid":true},"expectedInitialState":"reserved","identity":{"action":"retry-stage","actorId":"pipeline-system","authorizationDecisionId":"pipeline-authorization-c502ceb4","bindingFingerprint":"pipeline-confirmation-binding-c502ceb4","confirmationId":"pipeline-confirmation-c502ceb4","confirmationRequestId":"pipeline-confirmation-request-c502ceb4","createdAt":"2026-07-15T12:05:09.730Z","executionFingerprint":"pipeline-execution-e037fc56","idempotencyKey":"pipeline-idempotency-c502ceb4","identityFingerprint":"idempotency-identity-66b616ac","operation":"pipeline.stage.resume","policyVersion":"production-execution-idempotency-v1","projectSlug":"fatih-sultan-mehmet-in-i-stanbul-un-fethine-hazirlanisi-cfe77fd8-8350-4415-bc87-211e3d36c4d5","requestId":"pipeline-request-c502ceb4","riskLevel":"high","schemaVersion":"1","stage":"scenes"},"maxAttempts":3,"metadata":{"source":"server"},"policyContext":{"environment":"hosted","source":"server"},"requestedAt":"2026-07-15T12:05:09.730Z","reservationTtlSeconds":31536000,"schemaVersion":"1"}
