{
  "topic": "Atilla'nın Yükselişi",
  "summary": "Bu belgesel, Hun İmparatorluğu'nun en ünlü lideri Atilla'nın hayatını, yükselişini ve etkisini detaylarıyla anlatmaktadır. Atilla'nın gençlik yıllarından başlayarak, Hunların Avrupa'daki etkisini artırmasına ve Roma İmparatorluklarıyla olan çatışmalarına kadar uzanan süreç incelenir.",
  "historicalContext": "5. yüzyıl, Avrupa'da Roma İmparatorlukları zayıflamakta, çeşitli barbar kavimlerin baskısı altındadır. Hunlar, Orta Asya'dan batıya doğru ilerleyerek büyük bir güç haline gelir. Atilla, kardeşi Bleda ile birlikte Hunların liderliğini üstlenir ve kısa sürede tüm kabileleri birleştirerek Avrupa tarihinde derin izler bırakır.",
  "timeline": [
    "406: Hunların batıya göçü ve Avrupa'ya girişleri",
    "434: Atilla ve kardeşi Bleda'nın ortak liderliği",
    "445: Bleda'nın ölümü ve Atilla'nın tek lider olması",
    "447: Roma İmparatorluğu ile büyük çatışmalar",
    "451: Katalaun Savaşları ve Roma-Sakson ittifakı",
    "452: İtalya Seferi ve Papa I. Leo ile görüşme",
    "453: Atilla'nın ölümü ve Hun İmparatorluğu'nun dağılması"
  ],
  "characters": [
    "Atilla - Hun İmparatorluğu'nun tek lideri ve ana figür",
    "Bleda - Atilla'nın kardeşi ve başlangıçta ortak lider",
    "Flavius Aetius - Batı Roma İmparatorluğu komutanı",
    "Papa I. Leo - Roma papası, Atilla ile diplomasi yapan lider",
    "Valentinian III - Batı Roma İmparatoru"
  ],
  "locations": [
    "Orta Asya - Hunların köken bölgesi",
    "Hun İmparatorluğu merkezleri - Tuna Nehri çevresi",
    "Roma İmparatorluğu toprakları - İtalya, Gallia (Fransa)",
    "Katalaun Ovası - Büyük savaşın gerçekleştiği yer",
    "Roma - Papa I. Leo ile görüşme"
  ],
  "keyEvents": [
    "Atilla ve Bleda'nın ortak liderliği ve kabilelerin birleştirilmesi",
    "Bleda'nın ölümü ve Atilla'nın tek lider olması",
    "Hunların Roma İmparatorluğu sınırlarına saldırıları",
    "Katalaun Savaşları'nda Roma ve müttefiklerinin Hunlara karşı direnişi",
    "Atilla'nın İtalya seferi ve Papa I. Leo ile barış görüşmeleri",
    "Atilla'nın ani ölümü ve Hun İmparatorluğu'nun dağılması"
  ],
  "strategies": [
    "Atilla'nın kabileler arası ittifak kurarak güç birliği oluşturması",
    "Roma İmparatorluğu'nun bölünmüşlüğünü kullanarak siyasi ve askeri baskı uygulaması",
    "Hızlı atlı birlikleriyle ani ve etkili saldırılar düzenlemesi",
    "Diplomasi ve korku stratejisi ile Roma'ya karşı pazarlık yapması",
    "Düşmanlarını birbirine kırdırarak kendi üstünlüğünü pekiştirmesi"
  ],
  "controversies": [
    "Atilla'nın doğrudan Roma İmparatorluğu'nu yıkmayı hedefleyip hedeflemediği tartışması",
    "Hunların barbar mı yoksa organize bir devlet mi olduğu konusunda tarihçiler arasında görüş ayrılıkları",
    "Atilla'nın ölüm nedenleri: doğal mı yoksa suikast mı olduğu hâlâ net değil",
    "Roma ve Hunlar arasındaki savaşlarda sivillerin durumu ve etkileri",
    "Atilla'nın kişisel liderlik tarzı ve sertliği hakkında farklı bakış açıları"
  ],
  "interestingFacts": [
    "Atilla, 'Tanrı'nın Kırbacı' olarak anılmıştır.",
    "Atilla'nın ordusu, o dönemin en hızlı ve etkili atlı birliklerinden biriydi.",
    "Katalaun Savaşları, Avrupa'nın kaderini belirleyen önemli bir çatışmadır.",
    "Atilla'nın ölümünden sonra imparatorluk hızla parçalanmıştır.",
    "Papa I. Leo ile görüşmesi, Avrupa tarihinde kilisenin siyasi rolünü artıran önemli bir olaydır."
  ],
  "documentaryFlow": [
    "Giriş ve Atilla'nın önemi",
    "Hunların kökeni ve Avrupa'ya göçleri",
    "Atilla ve Bleda'nın liderlik dönemi",
    "Atilla'nın tek lider olması ve Roma ile ilişkileri",
    "Katalaun Savaşları ve büyük çatışmalar",
    "Atilla'nın İtalya Seferi ve Papa ile görüşmesi",
    "Atilla'nın ölümü ve Hun İmparatorluğu'nun çöküşü",
    "Atilla'nın mirası ve tarihsel etkileri",
    "Kapanış ve günümüze yansımalar"
  ],
  "sceneIdeas": [
    "Hunların Orta Asya'dan batıya göçü ve atlı orduların görüntüleri",
    "Atilla ve Bleda'nın kabile liderleriyle toplantısı",
    "Hunların Roma sınırlarına saldırı hazırlıkları",
    "Katalaun Ovası'nda büyük savaş sahnesi",
    "Atilla'nın Roma'da Papa I. Leo ile görüşmesi",
    "Atilla'nın ani ölüm haberi ve kabilelerin tepkisi",
    "Haritalar üzerinde Hun İmparatorluğu'nun genişlemesinin gösterilmesi",
    "Arkeolojik buluntular ve tarihi belgelerin tanıtımı"
  ],
  "imagePrompts": [
    "Sinematik ve gerçekçi Hun savaşçıları at sırtında, geniş bozkır manzarası arka planda, dramatik gün batımı ışığı",
    "Atilla'nın tahtında otururken betimlendiği detaylı portre, karanlık ve gizemli atmosfer",
    "Katalaun Ovası'nda büyük savaş sahnesi, binlerce asker atlı ve piyade olarak savaş halinde, toz ve duman efektleri",
    "Roma İmparatorluğu sınırlarında Hunların kampı, gece ateş ışıkları ve gölgelerle çevrili",
    "Papa I. Leo ile Atilla'nın Roma'da diplomatik görüşme anı, tarihi mimari ve detaylı kostümler",
    "Hunların Orta Asya'dan Avrupa'ya göç ederken geniş nehir ve dağ manzarası",
    "Harita üzerinde Hun İmparatorluğu'nun genişlemesini gösteren animasyonlu grafik",
    "Atilla'nın ölüm anı ve kabilelerin yas tutma sahnesi, dramatik ışıklandırma"
  ],
  "animationPrompts": [
    "Atilla'nın at üzerinde ilerleyişi, rüzgarla dalgalanan pelerin ve toz bulutları",
    "Hun ordusunun hızlı hareket eden atlı birlikleri, koordineli saldırı animasyonu",
    "Katalaun Savaşı dinamik harita animasyonu, askerlerin hareketleri ve çatışma noktaları",
    "Roma ve Hun güçlerinin karşılaşması, ok yağmuru ve kılıç darbeleri animasyonu",
    "Diplomatik görüşme esnasında ellerin tokalaşması ve mimiklerin detaylı hareketi",
    "Harita üzerinde Hunların göç rotasının çizilmesi, eski dünya atmosferi",
    "Atilla'nın ölümünden sonra Hun ordusunun dağılma animasyonu, askerlerin geri çekilişi",
    "Hunların geleneksel dans ve kutlama sahnesi, ritmik hareketler ve müzik uyumu"
  ],
  "musicIdeas": [
    "Orta Asya etkileri taşıyan etnik enstrümanlar (dombra, kaval)",
    "Dramatik ve epik orkestral temalar",
    "Atlı orduların hızını yansıtan tempolu davul ritimleri",
    "Gergin diplomasi sahnelerinde hafif gerilim müzikleri",
    "Savaş sahnelerinde yoğun ve güçlü yaylılar ile vurmalı çalgılar",
    "Hüzünlü ve yavaş melodiler Atilla'nın ölümü ve sonrasında",
    "Geleneksel Türk ve Hun motiflerinden esinlenmiş melodiler",
    "Doğa ve bozkır atmosferini yansıtan ambient müzikler"
  ],
  "soundEffects": [
    "Atlı atların ayak sesleri ve toz kalkışı",
    "Kılıç ve mızrak çarpışmaları",
    "Okların uçuş sesi ve hedefe isabet etme efektleri",
    "Savaş naraları ve askerlerin bağrışmaları",
    "Rüzgar sesi ve bozkır atmosferi",
    "Kamp ateşi çıtırtıları ve gece doğa sesleri",
    "Diplomatik görüşme ortamında hafif fısıltılar ve ortam sesi",
    "Yas ve matem sahnelerinde hüzünlü rüzgar sesi"
  ],
  "thumbnailIdeas": [
    "Atilla'nın güçlü ve kararlı portresi, arka planda savaş sahnesi bulanık",
    "Atlı bir Hun savaşçısının hızla ilerlerken çekilmiş dramatik görüntüsü",
    "Katalaun Savaşı'nın yoğun çatışma anından dinamik bir kare",
    "Atilla ile Papa I. Leo'nun yüz yüze geldiği tarihi görüşme anı",
    "Hun bayrağı ve Atilla'nın silueti arka planda güneşin doğuşu ile",
    "Harita üzerinde Hun İmparatorluğu'nun genişlemesini gösteren renkli grafik",
    "Atilla'nın ölüm haberi sonrası kabilelerin toplandığı dramatik sahne",
    "Hun savaşçılarının topluca bağlılık yemini ettiği güçlü kompozisyon"
  ],
  "youtubeTitles": [
    "Atilla'nın Yükselişi: Hunların Avrupa'yı Değiştiren Lideri",
    "Hun İmparatorluğu'nun Karanlık Gücü: Atilla'nın Hikayesi",
    "Atilla ve Katalaun Savaşları: Roma'nın Korkulu Rüyası",
    "Atilla'nın Avrupa Seferleri ve Efsanevi Liderliği",
    "Tanrı'nın Kırbacı: Atilla'nın Yükselişi ve Mirası",
    "Hunların Gizemli Lideri Atilla: İmparatorluğun Yükselişi ve Çöküşü",
    "Atilla'nın Sırları ve Roma İmparatorluğu'na Karşı Mücadelesi",
    "Atilla'nın Ölümü ve Hun İmparatorluğu'nun Dağılması"
  ],
  "sources": [
    "Priscus'un Hunlar hakkında yazdığı tarihi metinler",
    "Roma tarihçilerinin (Jordanes, Ammianus Marcellinus) kayıtları",
    "Arkeolojik kazı raporları ve Hun dönemi eserleri",
    "Modern tarih kitapları: \"Atilla the Hun\" - Patrick Howarth",
    "Orta Asya ve Avrupa tarihi üzerine akademik makaleler",
    "Katalaun Savaşları hakkında askeri analizler",
    "Papa I. Leo'nun yazışmaları ve Vatikan arşivleri",
    "Hun kültürü ve göçleri üzerine etnografik çalışmalar"
  ]
}